wev_awscodeartifact/__init__.py
wev_awscodeartifact/authoriser.py
wev_awscodeartifact/conftest.py
wev_awscodeartifact/plugin.py
wev_awscodeartifact/test_authoriser.py
wev_awscodeartifact/test_plugin.py
wev_awscodeartifact/test_version.py
wev_awscodeartifact/version.py
wev_awscodeartifact-1.0.0.dist-info/LICENSE
wev_awscodeartifact-1.0.0.dist-info/METADATA
wev_awscodeartifact-1.0.0.dist-info/WHEEL
wev_awscodeartifact-1.0.0.dist-info/entry_points.txt
wev_awscodeartifact-1.0.0.dist-info/top_level.txt
wev_awscodeartifact-1.0.0.dist-info/RECORD
