Metadata-Version: 2.1
Name: wev-awscodeartifact
Version: 1.0.0
Summary: "wev" plugin to support AWS CodeArtifact authorisation
Home-page: https://github.com/cariad/wev-awscodeartifact
Author: Cariad Eccleston
Author-email: cariad@hey.com
License: MIT License
Platform: UNKNOWN
Classifier: Development Status :: 5 - Production/Stable
Classifier: License :: OSI Approved :: MIT License
Classifier: Natural Language :: English
Classifier: Operating System :: OS Independent
Classifier: Programming Language :: Python :: 3 :: Only
Classifier: Programming Language :: Python :: 3.8
Classifier: Programming Language :: Python :: 3.9
Requires-Python: >=3.8
Requires-Dist: boto3 (>=1.16)
